vapory_git/__init__.py
vapory_git/config.py
vapory_git/helpers.py
vapory_git/io.py
vapory_git/vapory.py
vapory_git/version.py
Vapory_git-0.1.1.dist-info/LICENCE.txt
Vapory_git-0.1.1.dist-info/METADATA
Vapory_git-0.1.1.dist-info/WHEEL
Vapory_git-0.1.1.dist-info/top_level.txt
Vapory_git-0.1.1.dist-info/RECORD
