Metadata-Version: 2.1
Name: Vapory-git
Version: 0.1.1
Summary: git distribution: 3D rendering with Python and POV-Ray
Home-page: UNKNOWN
Author: Zulko
Author-email: UNKNOWN
License: see LICENSE.txt
Keywords: 3D POV-Ray Photo-realistic ray-tracing
Platform: UNKNOWN
